hymn-1.1.0.dist-info/METADATA
hymn-1.1.0.dist-info/WHEEL
hymn-1.1.0.dist-info/licenses/AUTHORS
hymn-1.1.0.dist-info/licenses/LICENSE
hymn/__init__.py
hymn/dsl.hy
hymn/macros.hy
hymn/mixins.hy
hymn/operations.hy
hymn/types/__init__.hy
hymn/types/continuation.hy
hymn/types/either.hy
hymn/types/identity.hy
hymn/types/lazy.hy
hymn/types/list.hy
hymn/types/maybe.hy
hymn/types/monad.hy
hymn/types/monadplus.hy
hymn/types/monoid.hy
hymn/types/reader.hy
hymn/types/state.hy
hymn/types/writer.hy
hymn/utils.hy
hymn-1.1.0.dist-info/RECORD
