Metadata-Version: 2.1
Name: hymn
Version: 1.1.0
Summary: Hy Monad Notation - a monad library for Hy
Keywords: hy lisp monad functional programming
Author-Email: Philip Xu <pyx@xrefactor.com>
License: BSD-New
Classifier: Development Status :: 4 - Beta
Classifier: Intended Audience :: Developers
Classifier: License :: OSI Approved :: BSD License
Classifier: Operating System :: OS Independent
Classifier: Programming Language :: Lisp
Classifier: Programming Language :: Python
Classifier: Programming Language :: Python :: 3
Classifier: Topic :: Software Development :: Libraries :: Python Modules
Project-URL: Homepage, https://github.com/pyx/hymn/
Requires-Python: <3.13,>=3.8
Requires-Dist: hy>=0.28.0
